{"format": "torch", "nodes": [{"name": "module", "id": 2361216747264, "class_name": "MyAwesomeModel(\n  (fc1): Linear(in_features=768, out_features=506, bias=True)\n  (fc2): Linear(in_features=506, out_features=165, bias=True)\n  (fc3): Linear(in_features=165, out_features=24, bias=True)\n  (fc4): Linear(in_features=24, out_features=1, bias=True)\n  (dropout_input): Dropout(p=0.2, inplace=False)\n  (dropout_hidden): Dropout(p=0.5, inplace=False)\n)", "parameters": [["fc1.weight", [506, 768]], ["fc1.bias", [506]], ["fc2.weight", [165, 506]], ["fc2.bias", [165]], ["fc3.weight", [24, 165]], ["fc3.bias", [24]], ["fc4.weight", [1, 24]], ["fc4.bias", [1]]], "output_shape": [[128, 1]], "num_parameters": [388608, 506, 83490, 165, 3960, 24, 24, 1]}], "edges": []}